[
  {
    "type": "release",
    "versionCode": 1272,
    "versionName": "1.2.7.2",
    "date": "2025.12.09",
    "description": [
      {
        "lang": "en",
        "text": "(Translated from Chinese by AI)\n1. New Feature: Allows switching between light/dark theme modes within the launcher.\n2. New Feature: Allows setting the volume of the video background.\n3. Fixed an issue where cancelling edits to the directional control key style would still take effect.\n4. Added compatibility detection for the Ixeris mod."
      },
      {
        "lang": "zh_CN",
        "text": "（若启动器内下载缓慢请使用网盘下载,64位的请下载arm64，不知道该下哪个的请下载all）\n1.新增功能：允许启动器内切换亮色/暗色主题模式\n2.新增功能：允许设置视频背景的音量\n3.修复编辑方向控制键样式时取消后依然生效的问题\n4.增加对Ixeris模组的兼容性检测"
      }
    ],
    "netdiskUrl": "https://pan.quark.cn/s/f827976924bb",
    "url": "https://github.com/FCL-Team/FoldCraftLauncher/releases/download/1.2.7.2/FCL-release-1.2.7.2-all.apk"
  }
]